ruds/__init__.py
ruds/base.py
ruds-0.0.1.dist-info/METADATA
ruds-0.0.1.dist-info/WHEEL
ruds-0.0.1.dist-info/licenses/LICENSE
ruds-0.0.1.dist-info/RECORD
